{
	"configurations" : 
	[
		{
			"directories" : 
			[
				{
					"build" : ".",
					"hasInstallRule" : true,
					"jsonFile" : "directory-.-7df478d7f3a80fae0329.json",
					"minimumCMakeVersion" : 
					{
						"string" : "3.12"
					},
					"projectIndex" : 0,
					"source" : ".",
					"targetIndexes" : 
					[
						0,
						1
					]
				}
			],
			"name" : "",
			"projects" : 
			[
				{
					"directoryIndexes" : 
					[
						0
					],
					"name" : "udh1_gazebo",
					"targetIndexes" : 
					[
						0,
						1
					]
				}
			],
			"targets" : 
			[
				{
					"directoryIndex" : 0,
					"id" : "udh1_gazebo_uninstall::@6890427a1f51a3e7e1df",
					"jsonFile" : "target-udh1_gazebo_uninstall-b8a9f117b61c0a823757.json",
					"name" : "udh1_gazebo_uninstall",
					"projectIndex" : 0
				},
				{
					"directoryIndex" : 0,
					"id" : "uninstall::@6890427a1f51a3e7e1df",
					"jsonFile" : "target-uninstall-4d5bdaa828376a5afe1d.json",
					"name" : "uninstall",
					"projectIndex" : 0
				}
			]
		}
	],
	"kind" : "codemodel",
	"paths" : 
	{
		"build" : "/home/joao/Navigation/build/udh1_gazebo",
		"source" : "/home/joao/Navigation/src/udh1_gazebo"
	},
	"version" : 
	{
		"major" : 2,
		"minor" : 3
	}
}
